Metadata-Version: 1.1
Name: guix
Version: 0.0.2
Summary: Make faster cross platform GUI
Home-page: UNKNOWN
Author: Venkataramana
Author-email: UNKNOWN
License: MIT
Keywords: Gui
Platform: UNKNOWN
Classifier: 
